shed_pi_module_utils/__init__.py
shed_pi_module_utils/base_protocol.py
shed_pi_module_utils/data_submission.py
shed_pi_module_utils/shed_pi_components/__init__.py
shed_pi_module_utils/shed_pi_components/ds18b20.py
shed_pi_module_utils/utils.py
shed_pi_module_utils-0.1.2.dist-info/METADATA
shed_pi_module_utils-0.1.2.dist-info/WHEEL
shed_pi_module_utils-0.1.2.dist-info/RECORD
